{"note":"This file is an internal implementation detail to speed up HTML report generation. Its format can change at any time. You might be looking for the JSON report: https://coverage.rtfd.io/cmd.html#cmd-json","format":5,"version":"7.12.0","globals":"cb7fd0d603f8f151b4beeaa06aa8b072","files":{"z_f9ecd2ed143243b9___init___py":{"hash":"42e6f3e8a4769ca2984ad36067ed374e","index":{"url":"z_f9ecd2ed143243b9___init___py.html","file":"src/updates2mqtt/__init__.py","description":"","nums":{"precision":0,"n_files":1,"n_statements":2,"n_excluded":0,"n_missing":0,"n_branches":0,"n_partial_branches":0,"n_missing_branches":0}}},"z_f9ecd2ed143243b9___main___py":{"hash":"a44d38ed644c7a9b3ba2e3e9cd5147c9","index":{"url":"z_f9ecd2ed143243b9___main___py.html","file":"src/updates2mqtt/__main__.py","description":"","nums":{"precision":0,"n_files":1,"n_statements":3,"n_excluded":0,"n_missing":3,"n_branches":2,"n_partial_branches":0,"n_missing_branches":2}}},"z_f9ecd2ed143243b9_app_py":{"hash":"aea5cddca4a9a62ff156c0ef7becc1d2","index":{"url":"z_f9ecd2ed143243b9_app_py.html","file":"src/updates2mqtt/app.py","description":"","nums":{"precision":0,"n_files":1,"n_statements":143,"n_excluded":0,"n_missing":31,"n_branches":42,"n_partial_branches":12,"n_missing_branches":16}}},"z_f9ecd2ed143243b9_config_py":{"hash":"748bfbab4062910fb0a2a5ff3c33d55b","index":{"url":"z_f9ecd2ed143243b9_config_py.html","file":"src/updates2mqtt/config.py","description":"","nums":{"precision":0,"n_files":1,"n_statements":109,"n_excluded":0,"n_missing":15,"n_branches":12,"n_partial_branches":3,"n_missing_branches":5}}},"z_f9ecd2ed143243b9_hass_formatter_py":{"hash":"8ac27731fe18210dd6675dd9d7e957fd","index":{"url":"z_f9ecd2ed143243b9_hass_formatter_py.html","file":"src/updates2mqtt/hass_formatter.py","description":"","nums":{"precision":0,"n_files":1,"n_statements":30,"n_excluded":0,"n_missing":8,"n_branches":12,"n_partial_branches":2,"n_missing_branches":6}}},"z_19f4f574b6be44c5___init___py":{"hash":"28b69e325bee1b632d6ecdf1812d9c8d","index":{"url":"z_19f4f574b6be44c5___init___py.html","file":"src/updates2mqtt/integrations/__init__.py","description":"","nums":{"precision":0,"n_files":1,"n_statements":0,"n_excluded":0,"n_missing":0,"n_branches":0,"n_partial_branches":0,"n_missing_branches":0}}},"z_19f4f574b6be44c5_docker_py":{"hash":"22eae16fd2e3e9b7c94b2dd65789fd8e","index":{"url":"z_19f4f574b6be44c5_docker_py.html","file":"src/updates2mqtt/integrations/docker.py","description":"","nums":{"precision":0,"n_files":1,"n_statements":283,"n_excluded":2,"n_missing":114,"n_branches":92,"n_partial_branches":20,"n_missing_branches":54}}},"z_19f4f574b6be44c5_git_utils_py":{"hash":"d909be2d6273eb25d3aa72446b75eab1","index":{"url":"z_19f4f574b6be44c5_git_utils_py.html","file":"src/updates2mqtt/integrations/git_utils.py","description":"","nums":{"precision":0,"n_files":1,"n_statements":40,"n_excluded":0,"n_missing":8,"n_branches":4,"n_partial_branches":0,"n_missing_branches":0}}},"z_f9ecd2ed143243b9_model_py":{"hash":"fa93092905491fc19eea6899621e45fd","index":{"url":"z_f9ecd2ed143243b9_model_py.html","file":"src/updates2mqtt/model.py","description":"","nums":{"precision":0,"n_files":1,"n_statements":54,"n_excluded":0,"n_missing":7,"n_branches":0,"n_partial_branches":0,"n_missing_branches":0}}},"z_f9ecd2ed143243b9_mqtt_py":{"hash":"b86b2cc4798c451b7d02944d7b26ae49","index":{"url":"z_f9ecd2ed143243b9_mqtt_py.html","file":"src/updates2mqtt/mqtt.py","description":"","nums":{"precision":0,"n_files":1,"n_statements":206,"n_excluded":0,"n_missing":83,"n_branches":50,"n_partial_branches":10,"n_missing_branches":32}}}}}